<?xml version="1.0" encoding="utf-8" ?><dwsync><file name="font-awesome.css" server="ftp.creativeboxee.com" local="3613504680" remote="321226350052619432" Dst="-1" /><file name="bootstrap.min.css" server="ftp.creativeboxee.com" local="3613504680" remote="321226350052619432" Dst="-1" /><file name="bootstrap.css" server="ftp.creativeboxee.com" local="3613504680" remote="321226350052619432" Dst="-1" /><file name="bootstrap-theme.min.css" server="ftp.creativeboxee.com" local="3613504680" remote="321226350052619432" Dst="-1" /><file name="bootstrap-theme.css" server="ftp.creativeboxee.com" local="3613504680" remote="321226350052619432" Dst="-1" /><file name="style.css" server="ftp.creativeboxee.com" local="3613504620" remote="321226350052619372" Dst="-1" /><file name="overwrite.css" server="ftp.creativeboxee.com" local="3613504620" remote="321226350052619372" Dst="-1" /><file name="font-awesome.min.css" server="ftp.creativeboxee.com" local="3613504620" remote="321226350052619372" Dst="-1" /></dwsync>